wuddz_crypto/__init__.py
wuddz_crypto/btc_chain.py
wuddz_crypto/docs.py
wuddz_crypto/main.py
wuddz_crypto/trx_chain.py
wuddz_crypto/wallet.py
wuddz_crypto-1.0.2.dist-info/METADATA
wuddz_crypto-1.0.2.dist-info/WHEEL
wuddz_crypto-1.0.2.dist-info/entry_points.txt
wuddz_crypto-1.0.2.dist-info/licenses/LICENSE
wuddz_crypto-1.0.2.dist-info/RECORD
