Metadata-Version: 2.4
Name: wuddz_crypto
Version: 1.0.2
Summary: Multi Blockchain Cryptocurrency App, Create HDWallets, Make Transactions & Check Balances.
Project-URL: Homepage, https://github.com/wuddz-devs/wuddz-crypto
Author-email: Wuddz-Devs <wuddz_devs@protonmail.com>
License: MIT License
License-File: LICENSE
Keywords: bit,bitcoin,btc,crypto,deposit,transfer,tronics,tronpy,trx,wallet
Classifier: License :: OSI Approved :: MIT License
Classifier: Programming Language :: Python
Classifier: Programming Language :: Python :: 3.7
Classifier: Programming Language :: Python :: 3.8
Classifier: Programming Language :: Python :: 3.9
Classifier: Programming Language :: Python :: 3.10
Requires-Python: >=3.7
Requires-Dist: bit
Requires-Dist: blockcypher
Requires-Dist: cryptography
Requires-Dist: hdwallet<=2.2.1
Requires-Dist: pycoingecko
Requires-Dist: requests
Requires-Dist: tronpy
